<nsim>
    <settings>
        <units>
            <mass> kg </mass>
            <length> km </length>
            <time> sec </time>
        </units>
        <start-date-time>1979-Jul-08 00:00:00</start-date-time>
    </settings>
    <universe>
        <body name="Sun">
            <radius> 6.960e5 </radius>
            <mass> 1.9884158281565063e+30</mass>
            <position> 0, 0, 0</position>
            <velocity> 0, 0, 0</velocity>
        </body>
        <body name="Jupiter">
            <radius> 71492 </radius>
            <mass> 1.898520845421447e+27</mass>
            <position> -5.874056956411636E+08,  5.390535124181495E+08,  1.094239091475520E+07</position>
            <velocity> -8.998744178073773E+00, -9.029906277144304E+00,  2.387129043666500E-01</velocity>
        </body>
        <body name="Voyager 2">
            <radius> 0.02 </radius>
            <mass> 721.9  </mass>
            <position>-5.858936348223692E+08,  5.372353148152831E+08,  1.103338952348754E+07</position>
            <velocity>-1.147779690363049E+01,  3.539159720239267E+00, -9.063673652480713E-01</velocity>
        </body>
    </universe>
</nsim>
